CHANGELOG.md
LICENSE
MANIFEST.in
README.md
setup.py
guidebook/__init__.py
guidebook/api_requestor.py
guidebook/exceptions.py
guidebook_api_python.egg-info/PKG-INFO
guidebook_api_python.egg-info/SOURCES.txt
guidebook_api_python.egg-info/dependency_links.txt
guidebook_api_python.egg-info/requires.txt
guidebook_api_python.egg-info/top_level.txt