Metadata-Version: 1.1
Name: guidebook-api-python
Version: 0.0.2
Summary: Python client for the Guidebook Open API.
Home-page: https://github.com/Guidebook/guidebook-api-python
Author: Guidebook
Author-email: web-team@guidebook.com
License: MIT
Platform: UNKNOWN
Classifier: License :: OSI Approved :: MIT License
Classifier: Programming Language :: Python :: 2.7
